slmtools/__init__.py
slmtools/gui.py
slmtools/version.py
slmtools/test/__init__.py
slmtools/test/flat.png
slmtools/test/test1.py
slmtools/test/test1_plot.py
slmtools-0.3.73.dist-info/AUTHORS
slmtools-0.3.73.dist-info/LICENSE
slmtools-0.3.73.dist-info/METADATA
slmtools-0.3.73.dist-info/WHEEL
slmtools-0.3.73.dist-info/top_level.txt
slmtools-0.3.73.dist-info/RECORD
