Metadata-Version: 2.1
Name: slmtools
Version: 0.3.73
Summary: Spatial light modulator in Python
Home-page: https://github.com/jacopoantonello/slmtools
Maintainer: The SLM Project Developers
License: GPLv3+
Platform: UNKNOWN
Classifier: Development Status :: 5 - Production/Stable
Classifier: Intended Audience :: Developers
Classifier: Topic :: Scientific/Engineering :: Physics
Classifier: License :: OSI Approved :: GNU General Public License v3 or later (GPLv3+)
Classifier: Programming Language :: Python :: 3
Requires-Python: >=3.7
License-File: LICENSE
License-File: AUTHORS
Requires-Dist: numpy
Requires-Dist: matplotlib
Requires-Dist: PyQt5
Requires-Dist: zernike
Requires-Dist: imageio
Requires-Dist: scikit-image
